gemmapy/__init__.py
gemmapy/_processors.py
gemmapy/_subprocessors.py
gemmapy/_validators.py
gemmapy/gemmapy_api.py
gemmapy/sdk/__init__.py
gemmapy/sdk/api_client.py
gemmapy/sdk/configuration.py
gemmapy/sdk/rest.py
gemmapy/sdk/api/__init__.py
gemmapy/sdk/api/default_api.py
gemmapy/sdk/models/__init__.py
gemmapy/sdk/models/annotation_search_result_value_object.py
gemmapy/sdk/models/annotation_value_object.py
gemmapy/sdk/models/annotation_with_usage_statistics_value_object.py
gemmapy/sdk/models/api_info_value_object.py
gemmapy/sdk/models/array_design_value_object.py
gemmapy/sdk/models/array_design_with_usage_statistics_value_object.py
gemmapy/sdk/models/audit_event_value_object.py
gemmapy/sdk/models/bibliographic_reference_value_object.py
gemmapy/sdk/models/bio_assay_value_object.py
gemmapy/sdk/models/bio_material_value_object.py
gemmapy/sdk/models/bio_sequence_value_object.py
gemmapy/sdk/models/build_info_value_object.py
gemmapy/sdk/models/category_with_usage_statistics_value_object.py
gemmapy/sdk/models/cell_level_characteristics_value_object.py
gemmapy/sdk/models/cell_type_assignment_value_object.py
gemmapy/sdk/models/characteristic_value_object.py
gemmapy/sdk/models/citation_value_object.py
gemmapy/sdk/models/composite_sequence_arg.py
gemmapy/sdk/models/composite_sequence_value_object.py
gemmapy/sdk/models/contrast_result_value_object.py
gemmapy/sdk/models/database_entry_arg.py
gemmapy/sdk/models/database_entry_value_object.py
gemmapy/sdk/models/dataset.py
gemmapy/sdk/models/dataset1.py
gemmapy/sdk/models/dataset10.py
gemmapy/sdk/models/dataset11.py
gemmapy/sdk/models/dataset12.py
gemmapy/sdk/models/dataset13.py
gemmapy/sdk/models/dataset14.py
gemmapy/sdk/models/dataset15.py
gemmapy/sdk/models/dataset16.py
gemmapy/sdk/models/dataset17.py
gemmapy/sdk/models/dataset18.py
gemmapy/sdk/models/dataset19.py
gemmapy/sdk/models/dataset2.py
gemmapy/sdk/models/dataset20.py
gemmapy/sdk/models/dataset3.py
gemmapy/sdk/models/dataset4.py
gemmapy/sdk/models/dataset5.py
gemmapy-2.0.3.dist-info/licenses/LICENSE.md
gemmapy-2.0.3.dist-info/METADATA
gemmapy-2.0.3.dist-info/WHEEL
gemmapy-2.0.3.dist-info/top_level.txt
gemmapy-2.0.3.dist-info/RECORD
