Metadata-Version: 2.4
Name: gemmapy
Version: 2.0.3
Summary: a Python Wrapper for the Gemma API
Keywords: gemma,bioinformatics
Requires-Python: >3.10
License-File: LICENSE.md
Requires-Dist: certifi>=14.05.14
Requires-Dist: six>=1.10
Requires-Dist: python_dateutil>=2.5.3
Requires-Dist: setuptools>=21.0.0
Requires-Dist: urllib3>=1.15.1
Requires-Dist: pandas
Requires-Dist: numpy
Requires-Dist: anndata
Requires-Dist: typing
Dynamic: license-file
